{
    "key": "group_5eb3fecf5461e",
    "title": "Flexible",
    "fields": [
        {
            "key": "field_5eb4026b6871d",
            "label": "Carte des menus",
            "name": "menus",
            "type": "flexible_content",
            "instructions": "",
            "required": 0,
            "conditional_logic": 0,
            "wrapper": {
                "width": "",
                "class": "",
                "id": ""
            },
            "layouts": {
                "layout_5eb4041368721": {
                    "key": "layout_5eb4041368721",
                    "name": "section",
                    "label": "Section",
                    "display": "block",
                    "sub_fields": [
                        {
                            "key": "field_5eb4041c68722",
                            "label": "Titre",
                            "name": "title",
                            "type": "text",
                            "instructions": "",
                            "required": 0,
                            "conditional_logic": 0,
                            "wrapper": {
                                "width": "",
                                "class": "",
                                "id": ""
                            },
                            "default_value": "",
                            "placeholder": "",
                            "prepend": "",
                            "append": "",
                            "maxlength": ""
                        },
                        {
                            "key": "field_5eb4042868723",
                            "label": "Description",
                            "name": "description",
                            "type": "textarea",
                            "instructions": "",
                            "required": 0,
                            "conditional_logic": 0,
                            "wrapper": {
                                "width": "",
                                "class": "",
                                "id": ""
                            },
                            "default_value": "",
                            "placeholder": "",
                            "maxlength": "",
                            "rows": 2,
                            "new_lines": ""
                        }
                    ],
                    "min": "",
                    "max": ""
                },
                "layout_5eb4029c83ad5": {
                    "key": "layout_5eb4029c83ad5",
                    "name": "dishes_list",
                    "label": " Liste de plats",
                    "display": "block",
                    "sub_fields": [
                        {
                            "key": "field_5eb4038a6871e",
                            "label": "Plats",
                            "name": "dishes",
                            "type": "repeater",
                            "instructions": "",
                            "required": 0,
                            "conditional_logic": 0,
                            "wrapper": {
                                "width": "",
                                "class": "",
                                "id": ""
                            },
                            "collapsed": "",
                            "min": 0,
                            "max": 0,
                            "layout": "table",
                            "button_label": "Ajouter un plat",
                            "sub_fields": [
                                {
                                    "key": "field_5eb403ab6871f",
                                    "label": "Nom du plat",
                                    "name": "name",
                                    "type": "text",
                                    "instructions": "",
                                    "required": 0,
                                    "conditional_logic": 0,
                                    "wrapper": {
                                        "width": "",
                                        "class": "",
                                        "id": ""
                                    },
                                    "default_value": "",
                                    "placeholder": "",
                                    "prepend": "",
                                    "append": "",
                                    "maxlength": ""
                                },
                                {
                                    "key": "field_5eb4044b68724",
                                    "label": "Ingrédients",
                                    "name": "ingredients",
                                    "type": "text",
                                    "instructions": "",
                                    "required": 0,
                                    "conditional_logic": 0,
                                    "wrapper": {
                                        "width": "",
                                        "class": "",
                                        "id": ""
                                    },
                                    "default_value": "",
                                    "placeholder": "",
                                    "prepend": "",
                                    "append": "",
                                    "maxlength": ""
                                },
                                {
                                    "key": "field_5eb403bd68720",
                                    "label": "Prix",
                                    "name": "price",
                                    "type": "number",
                                    "instructions": "",
                                    "required": 0,
                                    "conditional_logic": 0,
                                    "wrapper": {
                                        "width": "",
                                        "class": "",
                                        "id": ""
                                    },
                                    "default_value": "",
                                    "placeholder": "",
                                    "prepend": "",
                                    "append": "€",
                                    "min": "",
                                    "max": "",
                                    "step": ""
                                }
                            ]
                        }
                    ],
                    "min": "",
                    "max": ""
                },
                "layout_5eb4048468725": {
                    "key": "layout_5eb4048468725",
                    "name": "featured",
                    "label": "Produit phare",
                    "display": "block",
                    "sub_fields": [
                        {
                            "key": "field_5eb404a468728",
                            "label": "Photo",
                            "name": "picture",
                            "type": "image",
                            "instructions": "",
                            "required": 0,
                            "conditional_logic": 0,
                            "wrapper": {
                                "width": "30",
                                "class": "",
                                "id": ""
                            },
                            "return_format": "id",
                            "preview_size": "thumbnail",
                            "library": "all",
                            "min_width": "",
                            "min_height": "",
                            "min_size": "",
                            "max_width": "",
                            "max_height": "",
                            "max_size": "",
                            "mime_types": ""
                        },
                        {
                            "key": "field_5eb4048e68726",
                            "label": "Nom du plat",
                            "name": "name",
                            "type": "text",
                            "instructions": "",
                            "required": 0,
                            "conditional_logic": 0,
                            "wrapper": {
                                "width": "50",
                                "class": "",
                                "id": ""
                            },
                            "default_value": "",
                            "placeholder": "",
                            "prepend": "",
                            "append": "",
                            "maxlength": ""
                        },
                        {
                            "key": "field_5eb4049868727",
                            "label": "Prix",
                            "name": "price",
                            "type": "number",
                            "instructions": "",
                            "required": 0,
                            "conditional_logic": 0,
                            "wrapper": {
                                "width": "20",
                                "class": "",
                                "id": ""
                            },
                            "default_value": "",
                            "placeholder": "",
                            "prepend": "",
                            "append": "€",
                            "min": "",
                            "max": "",
                            "step": ""
                        }
                    ],
                    "min": "",
                    "max": ""
                }
            },
            "button_label": "Ajouter une disposition",
            "min": "",
            "max": ""
        }
    ],
    "location": [
        [
            {
                "param": "page_template",
                "operator": "==",
                "value": "templates\/flexible.php"
            }
        ]
    ],
    "menu_order": 0,
    "position": "normal",
    "style": "default",
    "label_placement": "top",
    "instruction_placement": "label",
    "hide_on_screen": "",
    "active": 1,
    "description": "Une carte des menus d'un restaurant de sushis",
    "modified": 1590390951
}