{
    "key": "group_5eb3b72085c68",
    "title": "Répéteur",
    "fields": [
        {
            "key": "field_5eb3b9043e661",
            "label": "L'équipe",
            "name": "team",
            "type": "repeater",
            "instructions": "",
            "required": 0,
            "conditional_logic": 0,
            "wrapper": {
                "width": "",
                "class": "",
                "id": ""
            },
            "collapsed": "field_5eb3bead3e663",
            "min": 0,
            "max": 0,
            "layout": "table",
            "button_label": "Ajouter un collaborateur",
            "sub_fields": [
                {
                    "key": "field_5eb3be993e662",
                    "label": "Photo",
                    "name": "picture",
                    "type": "image",
                    "instructions": "",
                    "required": 0,
                    "conditional_logic": 0,
                    "wrapper": {
                        "width": "",
                        "class": "",
                        "id": ""
                    },
                    "return_format": "id",
                    "preview_size": "thumbnail",
                    "library": "all",
                    "min_width": "",
                    "min_height": "",
                    "min_size": "",
                    "max_width": "",
                    "max_height": "",
                    "max_size": "",
                    "mime_types": ""
                },
                {
                    "key": "field_5eb3bead3e663",
                    "label": "Nom",
                    "name": "name",
                    "type": "text",
                    "instructions": "",
                    "required": 0,
                    "conditional_logic": 0,
                    "wrapper": {
                        "width": "",
                        "class": "",
                        "id": ""
                    },
                    "default_value": "",
                    "placeholder": "",
                    "prepend": "",
                    "append": "",
                    "maxlength": ""
                },
                {
                    "key": "field_5eb3beb73e664",
                    "label": "Poste",
                    "name": "occupation",
                    "type": "text",
                    "instructions": "",
                    "required": 0,
                    "conditional_logic": 0,
                    "wrapper": {
                        "width": "",
                        "class": "",
                        "id": ""
                    },
                    "default_value": "",
                    "placeholder": "",
                    "prepend": "",
                    "append": "",
                    "maxlength": ""
                },
                {
                    "key": "field_5eb3bef43e665",
                    "label": "Téléphone",
                    "name": "phone",
                    "type": "text",
                    "instructions": "",
                    "required": 0,
                    "conditional_logic": 0,
                    "wrapper": {
                        "width": "",
                        "class": "",
                        "id": ""
                    },
                    "default_value": "",
                    "placeholder": "",
                    "prepend": "",
                    "append": "",
                    "maxlength": ""
                },
                {
                    "key": "field_5eb3befa3e666",
                    "label": "E-mail",
                    "name": "mail",
                    "type": "email",
                    "instructions": "",
                    "required": 0,
                    "conditional_logic": 0,
                    "wrapper": {
                        "width": "",
                        "class": "",
                        "id": ""
                    },
                    "default_value": "",
                    "placeholder": "",
                    "prepend": "",
                    "append": ""
                }
            ]
        }
    ],
    "location": [
        [
            {
                "param": "page_template",
                "operator": "==",
                "value": "templates\/repeater.php"
            }
        ]
    ],
    "menu_order": 0,
    "position": "normal",
    "style": "default",
    "label_placement": "top",
    "instruction_placement": "label",
    "hide_on_screen": "",
    "active": 1,
    "description": "Mise en pratique du répéteur pour une page équipe",
    "modified": 1590391032
}